{
  "_fv": 34,
  "_type": "tool",
  "definition": {
    "renderType": 0,
    "texture": "kobold_iron_axe",
    "customModelName": "Normal",
    "name": "Kobold Iron Axe",
    "specialInfo": [],
    "creativeTab": {
      "value": "CUSTOM:KoboldCreativeTab"
    },
    "toolType": "Axe",
    "harvestLevel": 3,
    "efficiency": 5.0,
    "attackSpeed": 1.2,
    "enchantability": 14,
    "damageVsEntity": 7.0,
    "usageCount": 256,
    "blocksAffected": [],
    "hasGlow": false,
    "repairItems": [
      {
        "value": "CUSTOM:KoboldIronAxe"
      },
      {
        "value": "Items.IRON_INGOT"
      }
    ],
    "immuneToFire": false,
    "stayInGridWhenCrafting": false,
    "damageOnCrafting": false
  }
}